happy_tree_gallery-0.8.0-py3.7-nspkg.pth
rmnl/htg/VERSION
rmnl/htg/__init__.py
rmnl/htg/defaults.py
rmnl/htg/htg.py
rmnl/htg/meta_example.py
rmnl/htg/models.py
rmnl/htg/classes/__init__.py
rmnl/htg/classes/clean.py
rmnl/htg/classes/config.py
rmnl/htg/classes/index.py
rmnl/htg/classes/json.py
rmnl/htg/classes/resize.py
rmnl/htg/classes/resize_simple.py
rmnl/htg/classes/serve.py
rmnl/htg/commands/__init__.py
rmnl/htg/commands/album.py
rmnl/htg/commands/config.py
rmnl/htg/commands/groom.py
rmnl/htg/commands/index.py
rmnl/htg/commands/json.py
rmnl/htg/commands/resize.py
rmnl/htg/commands/util.py
rmnl/htg/imaging/__init__.py
rmnl/htg/imaging/average.py
rmnl/htg/imaging/resize_im.py
rmnl/htg/imaging/resize_pil.py
rmnl/htg/imaging/resize_sips.py
rmnl/htg/migrate/__init__.py
rmnl/htg/migrate/in2ex.py
rmnl/htg/utils/__init__.py
rmnl/htg/utils/aliased_group.py
rmnl/htg/utils/groom.py
rmnl/htg/utils/validate.py
happy_tree_gallery-0.8.0.dist-info/LICENSE
happy_tree_gallery-0.8.0.dist-info/METADATA
happy_tree_gallery-0.8.0.dist-info/WHEEL
happy_tree_gallery-0.8.0.dist-info/entry_points.txt
happy_tree_gallery-0.8.0.dist-info/namespace_packages.txt
happy_tree_gallery-0.8.0.dist-info/top_level.txt
happy_tree_gallery-0.8.0.dist-info/RECORD
